{
  "collectionName": "components_home_heroes",
  "info": {
    "displayName": "hero"
  },
  "options": {},
  "attributes": {
    "quote": {
      "type": "customField",
      "customField": "plugin::ckeditor5.CKEditor",
      "options": {
        "preset": "defaultHtml"
      }
    },
    "description": {
      "type": "customField",
      "customField": "plugin::ckeditor5.CKEditor",
      "options": {
        "preset": "defaultHtml"
      }
    },
    "image": {
      "type": "media",
      "multiple": false,
      "allowedTypes": [
        "images"
      ]
    }
  },
  "config": {}
}
